ai_models_panguweather_gfs/.model.py.swp
ai_models_panguweather_gfs/__init__.py
ai_models_panguweather_gfs/_version.py
ai_models_panguweather_gfs/model.py
ai_models_panguweather_gfs-0.0.11.dist-info/LICENSE
ai_models_panguweather_gfs-0.0.11.dist-info/METADATA
ai_models_panguweather_gfs-0.0.11.dist-info/WHEEL
ai_models_panguweather_gfs-0.0.11.dist-info/entry_points.txt
ai_models_panguweather_gfs-0.0.11.dist-info/top_level.txt
ai_models_panguweather_gfs-0.0.11.dist-info/RECORD
